[
	{
		"album": "Dream Believers",
		"release": "2023-03-29",
		"songs": [
			{
				"title": {
					"ja": "Dream Believers",
					"rom": "Dream Believers",
					"ko": "Dream Believers"
				},
				"artist": {
					"ja": "蓮ノ空女学院スクールアイドルクラブ",
					"rom": "Hasunosora Girls' High School Idol Club",
					"ko": "하스노소라 여학원 스쿨 아이돌 클럽"
				},
				"lyricist": {
					"ja": "畑 亜貴",
					"rom": "Aki Hata",
					"ko": "하타 아키"
				},
				"composer": {
					"ja": "渡辺拓也",
					"rom": "Takuya Watanabe",
					"ko": "와타나베 타쿠야"
				},
				"arranger": {
					"ja": "渡辺拓也",
					"rom": "Takuya Watanabe",
					"ko": "와타나베 타쿠야"
				},
				"link": "https://youtu.be/pFA9b7PkCOQ",
				"note": ""
			},
			{
				"title": {
					"ja": "On your mark",
					"rom": "On your mark",
					"ko": "On your mark"
				},
				"artist": {
					"ja": "蓮ノ空女学院スクールアイドルクラブ",
					"rom": "Hasunosora Girls' High School Idol Club",
					"ko": "하스노소라 여학원 스쿨 아이돌 클럽"
				},
				"lyricist": [
					{
						"ja": "Kanata Okajima",
						"rom": "Kanata Okajima",
						"ko": "Kanata Okajima"
					},
					{
						"ja": "Hayato Yamamoto",
						"rom": "Hayato Yamamoto",
						"ko": "Hayato Yamamoto"
					}
				],
				"composer": {
					"ja": "EFFY",
					"rom": "EFFY",
					"ko": "EFFY"
				},
				"arranger": {
					"ja": "EFFY",
					"rom": "EFFY",
					"ko": "EFFY"
				},
				"link": "https://youtu.be/Jqmyvux-ztY",
				"note": ""
			},
			{
				"title": {
					"ja": "水彩世界",
					"rom": "Suisai Sekai",
					"ko": "수채화 세계"
				},
				"artist": {
					"ja": "スリーズブーケ",
					"rom": "Cerise Bouquet",
					"ko": "스리즈 부케"
				},
				"lyricist": {
					"ja": "ケリー",
					"rom": "Kelly",
					"ko": "케리"
				},
				"composer": [
					{
						"ja": "栗原暁(Jazzin'Park)",
						"rom": "Satoru Kurihara(Jazzin'park)",
						"ko": "쿠리하라 사토루"
					},
					{
						"ja": "前田佑",
						"rom": "Tasuku Maeda",
						"ko": "마에다 타스쿠"
					}
				],
				"arranger": {
					"ja": "前田佑",
					"rom": "Tasuku Maeda",
					"ko": "마에다 타스쿠"
				},
				"link": "https://youtu.be/xt8pJ4riNA0",
				"note": ""
			},
			{
				"title": {
					"ja": "AWOKE",
					"rom": "AWOKE",
					"ko": "AWOKE"
				},
				"artist": {
					"ja": "DOLLCHESTRA",
					"rom": "DOLLCHESTRA",
					"ko": "DOLLCHESTRA"
				},
				"lyricist": {
					"ja": "TATSUNE",
					"rom": "TATSUNE",
					"ko": "TATSUNE"
				},
				"composer": [
					{
						"ja": "Kanata Okajima",
						"rom": "Kanata Okajima",
						"ko": "Kanata Okajima"
					},
					{
						"ja": "Hayato Yamamoto",
						"rom": "Hayato Yamamoto",
						"ko": "Hayato Yamamoto"
					}
				],
				"arranger": {
					"ja": "Hayato Yamamoto",
					"rom": "Hayato Yamamoto",
					"ko": "Hayato Yamamoto"
				},
				"link": "https://youtu.be/7mxDqSZH-sA",
				"note": ""
			},
			{
				"title": {
					"ja": "ド！ド！ド！",
					"rom": "Do! Do! Do!",
					"ko": "도! 도! 도!"
				},
				"artist": {
					"ja": "みらくらぱーく！",
					"rom": "Mira-Cra Park!",
					"ko": "미라쿠라파크!"
				},
				"lyricist": {
					"ja": "ろさ",
					"rom": "Rosa",
					"ko": "로사"
				},
				"composer": {
					"ja": "山本玲史",
					"rom": "Reiji Yamamoto",
					"ko": "야마모토 레이지"
				},
				"arranger": {
					"ja": "山本玲史",
					"rom": "Reiji Yamamoto",
					"ko": "야마모토 레이지"
				},
				"link": "https://youtu.be/5TXxIDBRPEI",
				"note": ""
			},
			{
				"title": {
					"ja": "永遠のEuphoria",
					"rom": "Eien no Euphoria",
					"ko": "영원의 유포리아"
				},
				"artist": {
					"ja": "蓮ノ空女学院スクールアイドルクラブ",
					"rom": "Hasunosora Girls' High School Idol Club",
					"ko": "하스노소라 여학원 스쿨 아이돌 클럽"
				},
				"lyricist": {
					"ja": "KOMU",
					"rom": "KOMU",
					"ko": "KOMU"
				},
				"composer": {
					"ja": "オオヤギヒロオ",
					"rom": "Hiroo Ooyagi",
					"ko": "오오야기 히로오"
				},
				"arranger": {
					"ja": "オオヤギヒロオ",
					"rom": "Hiroo Ooyagi",
					"ko": "오오야기 히로오"
				},
				"link": "https://youtu.be/hcYTaeVWGgs",
				"note": ""
			}
		]
	}
]